postcodeapi/__init__.py
postcodeapi/client.py
postcodeapi/exceptions.py
postcodeapi/utils.py
postcodeapi-1.2.1.dist-info/METADATA
postcodeapi-1.2.1.dist-info/RECORD
postcodeapi-1.2.1.dist-info/WHEEL
postcodeapi-1.2.1.dist-info/top_level.txt
