Metadata-Version: 2.1
Name: postcodeapi
Version: 1.2.1
Summary: An unofficial Python wrapper around the Postcode API v2
Home-page: http://github.com/roedesh/postcodeapi
Author: Ruud Schroën
Author-email: schroenruud@gmail.com
License: MIT
Platform: UNKNOWN
Requires-Dist: requests
